pc.v
module PC(
  // alpha
  output reg alpha_k1 = 0, 
  output reg alpha_k2 = 0, 
  output reg alpha_k3 = 0, 
  output reg alpha_k4 = 0, 
  output reg alpha_k5 = 0, 
  output reg alpha_k_ind = 0,
  output reg alpha_k_i = 0,
  output reg alpha_k_esito = 0,
  output reg alpha_k_dataout = 0,
  output reg alpha_k_mem1 = 0,
  output reg alpha_k_mem2 = 0,
  output reg [2:0]alpha_alu2 = 0, 
  output reg [2:0]alpha_alu3 = 0, 
  output reg [2:0]alpha_alu4 = 0, 
  // betareg 
  output reg beta_hd = 0,
  output reg beta_ind = 0,
  output reg beta_i = 0,
  output reg beta_esito = 0,
  output reg beta_datain = 0,
  output reg beta_dataout = 0,
  output reg beta_rdyin = 0,
  output reg beta_ackout = 0,
  output reg beta_mem = 0,
  // variabili di condizionamento
  input clock, 
  input rdy, ack,
  input [2:0]op,
  input eq, // eq(I, N)
  input ge, // ge(HD, N) === segno(HD - N)
  input hd0,
  input or_hd,
  input or10_hd
);

  //TODO: derivare forme in SP delle variabili di controllo e aggiornarle all'interno di un assign
  always
  begin
    #2; // 2tp di ritardo per omegaPC

    // TEST
    if (rdy && op == 0)
    begin
      beta_mem <= 1; // abilita scrittura in memoria
      alpha_k_mem1 <= 0; // lettura di M[HD]
      alpha_alu3 <= 0; // (+)
      alpha_k3 <= 0; // HD
      beta_hd <= 1; // abilita scrittura di HD + 1 -> HD
      beta_dataout <= 1; // abilita scrittura di M[HD] in DATAOUT
    end
    // TEST
    else if (rdy == 0 && op == 1)
    begin
      beta_mem <= 0; // disabilita scrittura in memoria
      alpha_k_mem1 <= 0; // lettura di M[HD]
      alpha_alu3 <= 1; // (-)
      alpha_k3 <= 0; // HD
      beta_hd <= 1; // abilita scrittura di HD - 1 -> HD
      beta_dataout <= 1; // abilita scrittura di M[HD] in DATAOUT
    end
  end





endmodule

confrontatore.v
/*
* Confrontatore con 2 ingressi da un bit: calcola 0 se i due bit in ingresso sono uguali, 1 altrimenti
*/

module CONFRONTATORE(output out, input x1, input x2);
  assign #2 out = x1 ^ x2; // operatore xor
endmodule

registro.v
/*
* Registro impulsato da N bit
*/
module REGISTRO(output [N-1:0]out, input [N-1:0]in, input clock, input beta);
  parameter N = 32;
  reg [N-1:0]val = 0;

  // Si scrive nel registro durante il fronte di alzata per evitare stati metastabili
  // all'avvio del programma, per esempio:
  // in un'interfaccia a transizione di livello il registro interno S ha il beta=1 costante.
  // Questo implica che all'avvio della simulazione venga scritto nel registro il valore della linea
  // di ingresso (per esempio la linea rdy). Se questa linea impiega un tempo t > 0 per stabilizzare, nel
  // registro viene scritto all'avvio della simulazione (perche` clock = 0 al tempo t=0 viene interpretato
  // come un negedge del segnale di clock) un valore instabile che dura fino al prossimo impulso del clock.
  // Utilizzando posedge ed avendo l'accortezza di inizializzare il registro a 0 (in cima, val = 0) e di
  // generare il segnale di clock partendo dal basso( ____|¯¯|____|¯¯|_) si evita questo problema, purche` al
  // prossimo impulso di clock l'ingresso del registro sia stabile.
  always @(posedge clock)
  begin
    if (beta)
      val <= in;
  end

  assign out = val;
endmodule

transizione_livello.v
module TRANSIZIONE_LIVELLO(output out, input in, input clock, input beta);

  wire s_out;
  reg contatore_mod_2 = 0; // conta mod 2 quante volte beta diventa 1

  REGISTRO#(1) s(s_out, in, clock, 1'b1);
  CONFRONTATORE c(out, s_out, contatore_mod_2);

  // 2tp di ritardo per il contatore modulo 2
  always @(beta)
  begin
    #2 contatore_mod_2 = contatore_mod_2 ^ beta;
  end

endmodule

memoria.v
/*
* Memoria a doppia porta da N posizioni ciascuna da M bit:
* - 1 porta in lettura/scrittura
* - 1 porta in lettura;
* Il ritardo di accesso in memoria e` parametrizzabile, di default e` uguale a 8tp.
* TODO: aggiornare documento di derivazione formale: la memoria e` a doppia porta, non tripla e va aggiunto il segnale di clock, beta, il valore di ingresso e rimuovere alpha.
*/
module MEMORIA(out1, out2, in, ind1, ind2, clock, beta);

  parameter N=1024;
  parameter M=32;
  parameter RITARDO=8;
  parameter IND_SIZE=$clog2(N);

  output [M-1:0]out1, out2;
  input [M-1:0]in;
  input [IND_SIZE-1:0]ind1, ind2;
  input clock;
  input beta; // beta = 1, abilita scrittura in mem[ind1]
  integer i;

  reg [M-1:0]mem[0:N-1];

  initial
  begin
    for (i=0; i<N; i++)
      mem[i] = 0;
  end

  always @(posedge clock)
  begin
    if(beta)
      mem[ind1] = in;
  end

  assign #RITARDO out1 = mem[ind1];
  assign #RITARDO out2 = mem[ind2];

endmodule

confrontatore_n.v

/*
* Confrontatore con 2 ingressi da N bit ciascuno: 
* calcola 0 se i bit del primo ingresso coincidono con quelli del secondo, 1 altrimenti.
* Il confrontatore e` parametrico nel numero dei bit per ingresso e nel ritardo di stabilizzazione,
* che di default e` pari a: 2tp (per i confrontatori da un bit) + (floor(N/8) + 1)tp
* poiche` le porte AND vengono disposte in serie secondo
* una struttura ad albero di arieta` 8.
*/

module CONFRONTATORE_N(output reg out, input [N-1:0]x1, input [N-1:0]x2);
  parameter N = 16;
  parameter RITARDO = 2 + N/8 + 1;

  genvar i;
  integer j;
  wire wires[0:N-1];

  generate
    for(i=0; i<N; i=i+1)
    begin
      CONFRONTATORE c_i(wires[i], x1[i], x2[i]);
    end
  endgenerate

  always @(x1 or x2)
  begin
    #RITARDO; // simula il ritardo delle porte AND in serie
    out = 1;
    for(j=0; j<N; j=j+1)
      out = out & ~wires[j];
    out = ~out;
  end

endmodule

alu.v
/*
* ALU con operandi a N bit. Implementa le operazioni di somma, sottrazione, incremento, decremento e divisione.
* Fornisce in output, oltre al risultato, anche un bit di segno.
*/
module ALU(output reg [N-1:0]z, output reg segno, input [N-1:0]x, input [N-1:0]y, input [2:0]alpha);
  parameter N = 32;
  parameter RITARDO = 10;

  always @(alpha or x or y)
  begin
    #RITARDO;
    case(alpha)
      0: z = x + y;
      1: z = x - y;
      2: z = x + 1;
      3: z = x - 1;
      4: z = y + 1;
      5: z = y - 1;
      6: z = x / y;
    endcase
    segno = ~z[N-1]; // bit di segno negato (i.e. 0 se il risultato e` negativo, 1 se e` positivo)
  end
endmodule

commutatore2.v
/*
* Commutatore da N bit a due vie con 2tp di ritardo
*/
module COMMUTATORE2 (output [N-1:0]out, input [N-1:0]x1, input [N-1:0]x2, input alpha);
  parameter N=32;
  
  assign #2 out = ((~alpha) ? x1 : x2);

endmodule

po.v
module PO(
  // output della rete
  output wire [ALU_SIZE-1:0]dataout_out,
  // variabili di condizionamento
  output wire rdy,
  output wire ack,
  output wire [2:0]op_out,
  output wire eq_out, // eq(I, N)
  output wire ge, // segno(HD - N)
  output wire hd0,
  output wire or_hd,
  output wire or10_hd,

  // clock
  input clock, 
  // alpha
  input alpha_k1, 
  input alpha_k2, 
  input alpha_k3, 
  input alpha_k4, 
  input alpha_k5, 
  input alpha_k_ind,
  input alpha_k_i,
  input alpha_k_esito,
  input alpha_k_dataout,
  input alpha_k_mem1, alpha_k_mem2,
  input [2:0]alpha_alu2, 
  input [2:0]alpha_alu3, 
  input [2:0]alpha_alu4, 
  // beta
  input beta_hd,
  input beta_ind,
  input beta_i,
  input beta_esito,
  input beta_datain,
  input beta_dataout,
  input beta_rdyin,
  input beta_ackout,
  input beta_mem,
  // altri input
  input [ALU_SIZE-1:0]datain_val,
  input [9:0]n_val,
  input [2:0]op_in,
  input rdy_in
);

  parameter ALU_SIZE = 32;
  parameter K1_SIZE = 32;
  parameter K2_SIZE = 32;
  parameter K3_SIZE = 11;
  parameter K4_SIZE = 11;
  parameter K5_SIZE = 11;
  parameter K_IND_SIZE = 10;
  parameter K_I_SIZE = 10;
  parameter K_ESITO_SIZE = 1;

  /******* CONNESSIONI ********/
  // registri
  wire [10:0]hd_out;
  wire [K_IND_SIZE-1:0]ind_out;
  wire [K_I_SIZE-1:0]i_out;
  wire [K_ESITO_SIZE-1:0]esito_out;
  wire [ALU_SIZE-1:0]datain_out;
  wire [9:0]n_out;

  // commutatori
  wire [K1_SIZE-1:0]k1_out;
  wire [K2_SIZE-1:0]k2_out;
  wire [K3_SIZE-1:0]k3_out;
  wire [K4_SIZE-1:0]k4_out;
  wire [K5_SIZE-1:0]k5_out;
  wire [K_IND_SIZE-1:0]k_ind_out;
  wire [K_I_SIZE-1:0]k_i_out;
  wire [K_ESITO_SIZE-1:0]k_esito_out;
  wire [ALU_SIZE-1:0]k_dataout_out;
  wire [10:0]k_mem1_out, k_mem2_out;

  // alu
  wire [ALU_SIZE-1:0]alu1_out, alu2_out, alu3_out, alu4_out;
  wire alu2_segno, alu3_segno, alu4_segno;

  // memoria
  wire [31:0]mem_out1, mem_out2;
  /****************************/


  /******* COMPONENTI *********/
  // registri
  REGISTRO#(11) hd(hd_out, alu3_out, clock, beta_hd);
  REGISTRO#(10) ind(ind_out, k_ind_out, clock, beta_ind);
  REGISTRO#(10) i(i_out, k_i_out, clock, beta_i);
  REGISTRO#(3) esito(esito_out, k_esito_out, clock, beta_esito);
  REGISTRO#(ALU_SIZE) datain(datain_out, datain_val, clock, 1'b1); // TODO: beta sempre = 1?
  REGISTRO#(ALU_SIZE) dataout(dataout_out, k_dataout_out, clock, beta_dataout);
  REGISTRO#(10) n(n_out, n_val, clock, 1'b1); //TODO: beta sempre = 1?
  REGISTRO#(3) op(op_out, op_in, clock, 1'b1); //TODO: beta sempre = 1?

  // commutatori
  COMMUTATORE2#(K1_SIZE) k1(k1_out, mem_out1, dataout_out, alpha_k1);
  COMMUTATORE2#(K2_SIZE) k2(k2_out, mem_out2, n_out, alpha_k2);
  COMMUTATORE2#(K3_SIZE) k3(k3_out, hd_out, ind_out, alpha_k3);
  COMMUTATORE2#(K4_SIZE) k4(k4_out, hd_out, i_out, alpha_k4);
  COMMUTATORE2#(K5_SIZE) k5(k5_out, 1, 2, alpha_k5);
  COMMUTATORE2#(K_IND_SIZE) k_ind(k_ind_out, alu4_out, alu3_out, alpha_k_ind);
  COMMUTATORE2#(K_I_SIZE) k_i(k_i_out, 1, alu4_out, alpha_k_i);
  COMMUTATORE2#(K_ESITO_SIZE) k_esito(k_esito_out, 0, 1, alpha_k_esito);
  COMMUTATORE2#(ALU_SIZE) k_dataout(k_dataout_out, mem_out1, alu2_out, alpha_k_dataout);

  COMMUTATORE2#(11) k_mem1(k_mem1_out, hd_out, alu3_out, alpha_k_mem1);
  COMMUTATORE2#(11) k_mem2(k_mem2_out, alu4_out, ind_out, alpha_k_mem2);

  // alu
  ALU#(ALU_SIZE) alu1(alu1_out, ge, hd_out, n_out, 1); // calcola segno(HD - N) === ge(HD, N)
  ALU#(ALU_SIZE) alu2(alu2_out, alu2_segno, k1_out, k2_out, alpha_alu2);
  ALU#(ALU_SIZE) alu3(alu3_out, alu3_segno, k3_out, 1, alpha_alu3);
  ALU#(ALU_SIZE) alu4(alu4_out, alu4_segno, k4_out, k5_out, alpha_alu4);

  // comparatore
  CONFRONTATORE_N#(K_I_SIZE) eq(eq_out, i_out, n_out);

  // memoria
  MEMORIA#(1024, 32) mem(mem_out1, mem_out2, datain_out, k_mem1_out, k_mem2_out, clock, beta_mem);

  // interfacce a transizione di livello
  TRANSIZIONE_LIVELLO ackout(ack, 1'b0, clock, beta_ackout); // in=0 trasforma ackout in un contatore modulo 2
  TRANSIZIONE_LIVELLO rdyin(rdy, rdy_in, clock, beta_rdyin);
  /****************************/


  /*****CALCOLO VARIABILI DI CONDIZIONAMENTO******/
  assign hd0 = hd_out[10]; // bit piu` significativo di HD
  assign or_hd = | hd_out; // or unario di HD
  assign or10_hd = | hd_out[10:1]; // or unario dei 10 bit piu` significativi di HD
  /***************************************/

endmodule

test_po.v
module test_po();
  // segnale di clock
  reg clock;

  // var. di controllo
  wire alpha_k1, alpha_k2, alpha_k3, alpha_k4, alpha_k5, alpha_k_ind, alpha_k_i;
  wire alpha_k_esito;
  wire alpha_k_dataout;
  wire alpha_k_mem1, alpha_k_mem2;
  wire [2:0]alpha_alu2, alpha_alu3, alpha_alu4;
  wire beta_hd, beta_ind, beta_i, beta_esito;
  wire beta_datain, beta_dataout;
  wire beta_rdyin, beta_ackout;
  wire beta_mem;

  // var. di condizionamento
  wire rdy, ack;
  wire op_out;
  wire eq, ge, hd0, or_hd, or10_hd;

  // ingressi
  reg [31:0]datain = 0;
  reg [9:0]n = 0;
  reg [2:0]op = 0;
  reg rdy_in = 0;

  wire signed [31:0]po_out;

  PO parte_operativa(
    // output
    po_out,
    rdy,
    ack,
    op_out,
    eq,
    ge,
    hd0,
    or_hd,
    or10_hd,
    // input
    clock, 
    alpha_k1, alpha_k2, alpha_k3, alpha_k4, alpha_k5, 
    alpha_k_ind, 
    alpha_k_i,
    alpha_k_esito,
    alpha_k_dataout,
    alpha_k_mem1, alpha_k_mem2,
    alpha_alu2, alpha_alu3, alpha_alu4, 
    beta_hd, beta_ind, beta_i, beta_esito, beta_datain, beta_dataout, 
    beta_rdyin, beta_ackout,
    beta_mem,
    datain,
    n,
    op,
    rdy_in
  );

  PC parte_controllo(
    // output
    alpha_k1, alpha_k2, alpha_k3, alpha_k4, alpha_k5, 
    alpha_k_ind, 
    alpha_k_i,
    alpha_k_esito,
    alpha_k_dataout,
    alpha_k_mem1, alpha_k_mem2,
    alpha_alu2, alpha_alu3, alpha_alu4, 
    beta_hd, beta_ind, beta_i, beta_esito, beta_datain, beta_dataout, 
    beta_rdyin, beta_ackout,
    beta_mem,
    // input
    clock, 
    rdy,
    ack,
    op,
    eq,
    ge,
    hd0,
    or_hd,
    or10_hd
  );

  always
  begin
    if (clock == 0)
      #25 clock = 1;
    else 
      #1 clock = 0;
  end


  initial
  begin
    $dumpfile("test_po.vcd");
    $dumpvars;
    datain <= 1023;
    rdy_in <= 1;
    #26 datain--;
    #26 datain--;
    #26 datain--;
    #26 datain--;
    #26 datain--;
    #100;
    rdy_in <= 0;
    op <= 1;

    #1000;
    $finish;
  end
endmodule

test_po.vcd
$date
	Sat Aug 31 18:46:13 2019
$end
$version
	Icarus Verilog
$end
$timescale
	1s
$end
$scope module test_po $end
$var wire 1 ! rdy $end
$var wire 32 " po_out [31:0] $end
$var wire 1 # or_hd $end
$var wire 1 $ or10_hd $end
$var wire 1 % op_out $end
$var wire 1 & hd0 $end
$var wire 1 ' ge $end
$var wire 1 ( eq $end
$var wire 1 ) beta_rdyin $end
$var wire 1 * beta_mem $end
$var wire 1 + beta_ind $end
$var wire 1 , beta_i $end
$var wire 1 - beta_hd $end
$var wire 1 . beta_esito $end
$var wire 1 / beta_dataout $end
$var wire 1 0 beta_datain $end
$var wire 1 1 beta_ackout $end
$var wire 1 2 alpha_k_mem2 $end
$var wire 1 3 alpha_k_mem1 $end
$var wire 1 4 alpha_k_ind $end
$var wire 1 5 alpha_k_i $end
$var wire 1 6 alpha_k_esito $end
$var wire 1 7 alpha_k_dataout $end
$var wire 1 8 alpha_k5 $end
$var wire 1 9 alpha_k4 $end
$var wire 1 : alpha_k3 $end
$var wire 1 ; alpha_k2 $end
$var wire 1 < alpha_k1 $end
$var wire 3 = alpha_alu4 [2:0] $end
$var wire 3 > alpha_alu3 [2:0] $end
$var wire 3 ? alpha_alu2 [2:0] $end
$var wire 1 @ ack $end
$var reg 1 A clock $end
$var reg 32 B datain [31:0] $end
$var reg 10 C n [9:0] $end
$var reg 3 D op [2:0] $end
$var reg 1 E rdy_in $end
$scope module parte_controllo $end
$var wire 1 A clock $end
$var wire 3 F op [2:0] $end
$var wire 1 ! rdy $end
$var wire 1 # or_hd $end
$var wire 1 $ or10_hd $end
$var wire 1 & hd0 $end
$var wire 1 ' ge $end
$var wire 1 ( eq $end
$var wire 1 @ ack $end
$var reg 3 G alpha_alu2 [2:0] $end
$var reg 3 H alpha_alu3 [2:0] $end
$var reg 3 I alpha_alu4 [2:0] $end
$var reg 1 < alpha_k1 $end
$var reg 1 ; alpha_k2 $end
$var reg 1 : alpha_k3 $end
$var reg 1 9 alpha_k4 $end
$var reg 1 8 alpha_k5 $end
$var reg 1 7 alpha_k_dataout $end
$var reg 1 6 alpha_k_esito $end
$var reg 1 5 alpha_k_i $end
$var reg 1 4 alpha_k_ind $end
$var reg 1 3 alpha_k_mem1 $end
$var reg 1 2 alpha_k_mem2 $end
$var reg 1 1 beta_ackout $end
$var reg 1 0 beta_datain $end
$var reg 1 / beta_dataout $end
$var reg 1 . beta_esito $end
$var reg 1 - beta_hd $end
$var reg 1 , beta_i $end
$var reg 1 + beta_ind $end
$var reg 1 * beta_mem $end
$var reg 1 ) beta_rdyin $end
$upscope $end
$scope module parte_operativa $end
$var wire 3 J alpha_alu2 [2:0] $end
$var wire 3 K alpha_alu3 [2:0] $end
$var wire 3 L alpha_alu4 [2:0] $end
$var wire 1 < alpha_k1 $end
$var wire 1 ; alpha_k2 $end
$var wire 1 : alpha_k3 $end
$var wire 1 9 alpha_k4 $end
$var wire 1 8 alpha_k5 $end
$var wire 1 7 alpha_k_dataout $end
$var wire 1 6 alpha_k_esito $end
$var wire 1 5 alpha_k_i $end
$var wire 1 4 alpha_k_ind $end
$var wire 1 3 alpha_k_mem1 $end
$var wire 1 2 alpha_k_mem2 $end
$var wire 1 1 beta_ackout $end
$var wire 1 0 beta_datain $end
$var wire 1 / beta_dataout $end
$var wire 1 . beta_esito $end
$var wire 1 - beta_hd $end
$var wire 1 , beta_i $end
$var wire 1 + beta_ind $end
$var wire 1 * beta_mem $end
$var wire 1 ) beta_rdyin $end
$var wire 1 A clock $end
$var wire 32 M datain_val [31:0] $end
$var wire 10 N n_val [9:0] $end
$var wire 3 O op_in [2:0] $end
$var wire 1 E rdy_in $end
$var wire 1 ! rdy $end
$var wire 1 # or_hd $end
$var wire 1 $ or10_hd $end
$var wire 3 P op_out [2:0] $end
$var wire 10 Q n_out [9:0] $end
$var wire 32 R mem_out2 [31:0] $end
$var wire 32 S mem_out1 [31:0] $end
$var wire 11 T k_mem2_out [10:0] $end
$var wire 11 U k_mem1_out [10:0] $end
$var wire 10 V k_ind_out [9:0] $end
$var wire 10 W k_i_out [9:0] $end
$var wire 1 X k_esito_out $end
$var wire 32 Y k_dataout_out [31:0] $end
$var wire 11 Z k5_out [10:0] $end
$var wire 11 [ k4_out [10:0] $end
$var wire 11 \ k3_out [10:0] $end
$var wire 32 ] k2_out [31:0] $end
$var wire 32 ^ k1_out [31:0] $end
$var wire 10 _ ind_out [9:0] $end
$var wire 10 ` i_out [9:0] $end
$var wire 11 a hd_out [10:0] $end
$var wire 1 & hd0 $end
$var wire 1 ' ge $end
$var wire 1 b esito_out $end
$var wire 1 ( eq_out $end
$var wire 32 c dataout_out [31:0] $end
$var wire 32 d datain_out [31:0] $end
$var wire 1 e alu4_segno $end
$var wire 32 f alu4_out [31:0] $end
$var wire 1 g alu3_segno $end
$var wire 32 h alu3_out [31:0] $end
$var wire 1 i alu2_segno $end
$var wire 32 j alu2_out [31:0] $end
$var wire 32 k alu1_out [31:0] $end
$var wire 1 @ ack $end
$scope module ackout $end
$var wire 1 1 beta $end
$var wire 1 A clock $end
$var wire 1 l in $end
$var wire 1 m s_out $end
$var wire 1 @ out $end
$var reg 1 n contatore_mod_2 $end
$scope module c $end
$var wire 1 @ out $end
$var wire 1 n x2 $end
$var wire 1 m x1 $end
$upscope $end
$scope module s $end
$var wire 1 o beta $end
$var wire 1 A clock $end
$var wire 1 l in $end
$var wire 1 m out $end
$var reg 1 m val $end
$upscope $end
$upscope $end
$scope module alu1 $end
$var wire 3 p alpha [2:0] $end
$var wire 32 q x [31:0] $end
$var wire 32 r y [31:0] $end
$var reg 1 ' segno $end
$var reg 32 s z [31:0] $end
$upscope $end
$scope module alu2 $end
$var wire 3 t alpha [2:0] $end
$var wire 32 u y [31:0] $end
$var wire 32 v x [31:0] $end
$var reg 1 i segno $end
$var reg 32 w z [31:0] $end
$upscope $end
$scope module alu3 $end
$var wire 3 x alpha [2:0] $end
$var wire 32 y x [31:0] $end
$var wire 32 z y [31:0] $end
$var reg 1 g segno $end
$var reg 32 { z [31:0] $end
$upscope $end
$scope module alu4 $end
$var wire 3 | alpha [2:0] $end
$var wire 32 } x [31:0] $end
$var wire 32 ~ y [31:0] $end
$var reg 1 e segno $end
$var reg 32 !" z [31:0] $end
$upscope $end
$scope module datain $end
$var wire 1 "" beta $end
$var wire 1 A clock $end
$var wire 32 #" in [31:0] $end
$var wire 32 $" out [31:0] $end
$var reg 32 %" val [31:0] $end
$upscope $end
$scope module dataout $end
$var wire 1 / beta $end
$var wire 1 A clock $end
$var wire 32 &" out [31:0] $end
$var wire 32 '" in [31:0] $end
$var reg 32 (" val [31:0] $end
$upscope $end
$scope module eq $end
$var wire 10 )" x2 [9:0] $end
$var wire 10 *" x1 [9:0] $end
$var reg 1 ( out $end
$var integer 32 +" j [31:0] $end
$scope begin genblk1[0] $end
$scope module c_i $end
$var wire 1 ," out $end
$var wire 1 -" x1 $end
$var wire 1 ." x2 $end
$upscope $end
$upscope $end
$scope begin genblk1[1] $end
$scope module c_i $end
$var wire 1 /" out $end
$var wire 1 0" x1 $end
$var wire 1 1" x2 $end
$upscope $end
$upscope $end
$scope begin genblk1[2] $end
$scope module c_i $end
$var wire 1 2" out $end
$var wire 1 3" x1 $end
$var wire 1 4" x2 $end
$upscope $end
$upscope $end
$scope begin genblk1[3] $end
$scope module c_i $end
$var wire 1 5" out $end
$var wire 1 6" x1 $end
$var wire 1 7" x2 $end
$upscope $end
$upscope $end
$scope begin genblk1[4] $end
$scope module c_i $end
$var wire 1 8" out $end
$var wire 1 9" x1 $end
$var wire 1 :" x2 $end
$upscope $end
$upscope $end
$scope begin genblk1[5] $end
$scope module c_i $end
$var wire 1 ;" out $end
$var wire 1 <" x1 $end
$var wire 1 =" x2 $end
$upscope $end
$upscope $end
$scope begin genblk1[6] $end
$scope module c_i $end
$var wire 1 >" out $end
$var wire 1 ?" x1 $end
$var wire 1 @" x2 $end
$upscope $end
$upscope $end
$scope begin genblk1[7] $end
$scope module c_i $end
$var wire 1 A" out $end
$var wire 1 B" x1 $end
$var wire 1 C" x2 $end
$upscope $end
$upscope $end
$scope begin genblk1[8] $end
$scope module c_i $end
$var wire 1 D" out $end
$var wire 1 E" x1 $end
$var wire 1 F" x2 $end
$upscope $end
$upscope $end
$scope begin genblk1[9] $end
$scope module c_i $end
$var wire 1 G" out $end
$var wire 1 H" x1 $end
$var wire 1 I" x2 $end
$upscope $end
$upscope $end
$upscope $end
$scope module esito $end
$var wire 1 . beta $end
$var wire 1 A clock $end
$var wire 3 J" in [2:0] $end
$var wire 3 K" out [2:0] $end
$var reg 3 L" val [2:0] $end
$upscope $end
$scope module hd $end
$var wire 1 - beta $end
$var wire 1 A clock $end
$var wire 11 M" in [10:0] $end
$var wire 11 N" out [10:0] $end
$var reg 11 O" val [10:0] $end
$upscope $end
$scope module i $end
$var wire 1 , beta $end
$var wire 1 A clock $end
$var wire 10 P" out [9:0] $end
$var wire 10 Q" in [9:0] $end
$var reg 10 R" val [9:0] $end
$upscope $end
$scope module ind $end
$var wire 1 + beta $end
$var wire 1 A clock $end
$var wire 10 S" out [9:0] $end
$var wire 10 T" in [9:0] $end
$var reg 10 U" val [9:0] $end
$upscope $end
$scope module k1 $end
$var wire 1 < alpha $end
$var wire 32 V" x2 [31:0] $end
$var wire 32 W" x1 [31:0] $end
$var wire 32 X" out [31:0] $end
$upscope $end
$scope module k2 $end
$var wire 1 ; alpha $end
$var wire 32 Y" x2 [31:0] $end
$var wire 32 Z" x1 [31:0] $end
$var wire 32 [" out [31:0] $end
$upscope $end
$scope module k3 $end
$var wire 1 : alpha $end
$var wire 11 \" x1 [10:0] $end
$var wire 11 ]" x2 [10:0] $end
$var wire 11 ^" out [10:0] $end
$upscope $end
$scope module k4 $end
$var wire 1 9 alpha $end
$var wire 11 _" x1 [10:0] $end
$var wire 11 `" x2 [10:0] $end
$var wire 11 a" out [10:0] $end
$upscope $end
$scope module k5 $end
$var wire 1 8 alpha $end
$var wire 11 b" x1 [10:0] $end
$var wire 11 c" x2 [10:0] $end
$var wire 11 d" out [10:0] $end
$upscope $end
$scope module k_dataout $end
$var wire 1 7 alpha $end
$var wire 32 e" x2 [31:0] $end
$var wire 32 f" x1 [31:0] $end
$var wire 32 g" out [31:0] $end
$upscope $end
$scope module k_esito $end
$var wire 1 6 alpha $end
$var wire 1 h" x1 $end
$var wire 1 i" x2 $end
$var wire 1 X out $end
$upscope $end
$scope module k_i $end
$var wire 1 5 alpha $end
$var wire 10 j" x1 [9:0] $end
$var wire 10 k" x2 [9:0] $end
$var wire 10 l" out [9:0] $end
$upscope $end
$scope module k_ind $end
$var wire 1 4 alpha $end
$var wire 10 m" x1 [9:0] $end
$var wire 10 n" x2 [9:0] $end
$var wire 10 o" out [9:0] $end
$upscope $end
$scope module k_mem1 $end
$var wire 1 3 alpha $end
$var wire 11 p" x1 [10:0] $end
$var wire 11 q" x2 [10:0] $end
$var wire 11 r" out [10:0] $end
$upscope $end
$scope module k_mem2 $end
$var wire 1 2 alpha $end
$var wire 11 s" x1 [10:0] $end
$var wire 11 t" x2 [10:0] $end
$var wire 11 u" out [10:0] $end
$upscope $end
$scope module mem $end
$var wire 1 * beta $end
$var wire 1 A clock $end
$var wire 32 v" in [31:0] $end
$var wire 10 w" ind1 [9:0] $end
$var wire 10 x" ind2 [9:0] $end
$var wire 32 y" out1 [31:0] $end
$var wire 32 z" out2 [31:0] $end
$var integer 32 {" i [31:0] $end
$upscope $end
$scope module n $end
$var wire 1 |" beta $end
$var wire 1 A clock $end
$var wire 10 }" in [9:0] $end
$var wire 10 ~" out [9:0] $end
$var reg 10 !# val [9:0] $end
$upscope $end
$scope module op $end
$var wire 1 "# beta $end
$var wire 1 A clock $end
$var wire 3 ## in [2:0] $end
$var wire 3 $# out [2:0] $end
$var reg 3 %# val [2:0] $end
$upscope $end
$scope module rdyin $end
$var wire 1 ) beta $end
$var wire 1 A clock $end
$var wire 1 E in $end
$var wire 1 &# s_out $end
$var wire 1 ! out $end
$var reg 1 '# contatore_mod_2 $end
$scope module c $end
$var wire 1 ! out $end
$var wire 1 '# x2 $end
$var wire 1 &# x1 $end
$upscope $end
$scope module s $end
$var wire 1 (# beta $end
$var wire 1 A clock $end
$var wire 1 E in $end
$var wire 1 &# out $end
$var reg 1 &# val $end
$upscope $end
$upscope $end
$upscope $end
$upscope $end
$enddefinitions $end
#0
$dumpvars
1(#
0'#
0&#
b0 %#
b0 $#
b0 ##
1"#
b0 !#
b0 ~"
b0 }"
1|"
b10000000000 {"
bx z"
bx y"
bx x"
bx w"
b0 v"
bx u"
b0 t"
bx s"
bx r"
bx q"
b0 p"
bx o"
bx n"
bx m"
bx l"
bx k"
b1 j"
1i"
0h"
bx g"
bx f"
bx e"
bx d"
b10 c"
b1 b"
bx a"
b0 `"
b0 _"
bx ^"
b0 ]"
b0 \"
bx ["
bx Z"
b0 Y"
bx X"
bx W"
b0 V"
b0 U"
bx T"
b0 S"
b0 R"
bx Q"
b0 P"
b0 O"
b0 N"
bx M"
b0 L"
b0 K"
b0x J"
0I"
0H"
xG"
0F"
0E"
xD"
0C"
0B"
xA"
0@"
0?"
x>"
0="
0<"
x;"
0:"
09"
x8"
07"
06"
x5"
04"
03"
x2"
01"
00"
x/"
0."
0-"
x,"
bx +"
b0 *"
b0 )"
b0 ("
bx '"
b0 &"
b0 %"
b0 $"
b1111111111 #"
1""
bx !"
b0xxxxxxxxxxx ~
b0xxxxxxxxxxx }
b0 |
bx {
b1 z
b0xxxxxxxxxxx y
b0 x
bx w
bx v
bx u
b0 t
bx s
b0 r
b0 q
b1 p
1o
0n
0m
0l
bx k
bx j
xi
bx h
xg
bx f
xe
b0 d
b0 c
0b
b0 a
b0 `
b0 _
bx ^
bx ]
bx \
bx [
bx Z
bx Y
xX
bx W
bx V
bx U
bx T
bx S
bx R
b0 Q
b0 P
b0 O
b0 N
b1111111111 M
b0 L
b0 K
b0 J
b0 I
b0 H
b0 G
b0 F
1E
b0 D
b0 C
b1111111111 B
xA
x@
b0 ?
b0 >
b0 =
0<
0;
0:
09
08
07
06
05
04
03
02
01
00
0/
0.
0-
0,
0+
0*
0)
x(
x'
0&
0%
0$
0#
b0 "
x!
$end
#1
0A
#2
b0 w"
b0 U
b0 r"
0G"
0D"
0A"
0>"
0;"
08"
05"
02"
0/"
0,"
b1 W
b1 Q"
b1 l"
0!
0@
b0 }
b0 [
b0 a"
b0 y
b0 \
b0 ^"
b0 J"
0X
b1 ~
b1 Z
b1 d"
#4
b1010 +"
0(
#8
b1010 +"
0(
#10
b1 s"
b1 k"
b1 m"
b1 q"
b1 n"
b1 M"
b0 S
b0 W"
b0 f"
b0 y"
0e
b1 f
b1 !"
0g
b1 h
b1 {
0'
b0 k
b0 s
#12
b1 x"
b1 T
b1 u"
b1 V
b1 T"
b1 o"
b0 Y
b0 '"
b0 g"
b0 ^
b0 v
b0 X"
b1010 +"
0(
#16
b1010 +"
0(
#20
b1010 +"
0(
b0 R
b0 Z"
b0 z"
#22
b0 ]
b0 u
b0 ["
#24
b1010 +"
0(
#26
b1111111110 d
b1111111110 $"
b1111111110 v"
b1111111110 %"
1&#
1A
b1111111110 B
b1111111110 M
b1111111110 #"
#27
0A
#28
1!
b1010 +"
0(
#30
1/
1-
1*
#32
b1010 +"
0(
0i
b0 j
b0 w
b0 e"
#36
b1010 +"
0(
#40
b1010 +"
0(
#44
b1010 +"
0(
#48
b1010 +"
0(
#52
b1111111101 d
b1111111101 $"
b1111111101 v"
b1111111101 %"
1#
b1 q
b1 a
b1 N"
b1 O"
b1 \"
b1 _"
b1 p"
b1010 +"
0(
1A
b1111111101 B
b1111111101 M
b1111111101 #"
#53
0A
