memoria.v
/*
* Memoria a doppia porta da N posizioni ciascuna da M bit:
* - 1 porta in lettura/scrittura
* - 1 porta in lettura;
* Il ritardo di accesso in memoria e` parametrizzabile, di default e` uguale a 8tp.
* TODO: aggiornare documento di derivazione formale: la memoria e` a doppia porta, non tripla e va aggiunto il segnale di clock, beta, il valore di ingresso e rimuovere alpha.
*/
module MEMORIA(out1, out2, in, ind1, ind2, clock, beta);

  parameter N=1024;
  parameter M=32;
  parameter RITARDO=8;
  parameter IND_SIZE=$clog2(N);

  output [M-1:0]out1, out2;
  input [M-1:0]in;
  input [IND_SIZE-1:0]ind1, ind2;
  input clock;
  input beta; // beta = 1, abilita scrittura in mem[ind1]
  integer i;

  reg [M-1:0]mem[0:N-1];

  initial
  begin
    for (i=0; i<N; i++)
      mem[i] = 0;
  end

  always @(negedge clock)
  begin
    if(beta)
      mem[ind1] = in;
  end

  assign #RITARDO out1 = mem[ind1];
  assign #RITARDO out2 = mem[ind2];

endmodule

test_memoria.v
module test_memoria();
  reg [31:0]x = 0;
  reg clock = 1;
  reg beta = 0;
  wire [31:0]out1;
  wire [31:0]out2;
  reg [9:0]ind1;
  reg [9:0]ind2;

  always
  begin
    if (clock == 0)
      #40 clock = 1;
    else 
      #1 clock = 0;
  end

  MEMORIA memoria(out1, out2, x, ind1, ind2, clock, beta);

  initial
  begin
    $dumpfile("test_memoria.vcd");
    $dumpvars;
    beta = 0;
    #4;
    beta = 1;
    x <= 42;
    ind1 <= 0;
    ind2 <= 0;
    beta <= 1;
    #100;
    x <= 128;
    ind2 <= 1023;
    beta <= 1;
    #16;
    ind1 <= 1023;
    x <= 256;
    #100;
    $finish;
  end
endmodule

test_memoria.vcd
$date
	Thu Aug 29 20:10:11 2019
$end
$version
	Icarus Verilog
$end
$timescale
	1s
$end
$scope module test_memoria $end
$var wire 32 ! out2 [31:0] $end
$var wire 32 " out1 [31:0] $end
$var reg 1 # beta $end
$var reg 1 $ clock $end
$var reg 10 % ind1 [9:0] $end
$var reg 10 & ind2 [9:0] $end
$var reg 32 ' x [31:0] $end
$scope module memoria $end
$var wire 1 # beta $end
$var wire 1 $ clock $end
$var wire 32 ( in [31:0] $end
$var wire 10 ) ind1 [9:0] $end
$var wire 10 * ind2 [9:0] $end
$var wire 32 + out1 [31:0] $end
$var wire 32 , out2 [31:0] $end
$var integer 32 - i [31:0] $end
$upscope $end
$upscope $end
$enddefinitions $end
#0
$dumpvars
b10000000000 -
bx ,
bx +
bx *
bx )
b0 (
b0 '
bx &
bx %
1$
0#
bx "
bx !
$end
#1
0$
#4
b0 &
b0 *
b0 %
b0 )
b101010 '
b101010 (
1#
#12
b0 !
b0 ,
b0 "
b0 +
#41
1$
#42
0$
#50
b101010 "
b101010 +
b101010 !
b101010 ,
#82
1$
#83
0$
#104
b1111111111 &
b1111111111 *
b10000000 '
b10000000 (
#112
b0 !
b0 ,
#120
b100000000 '
b100000000 (
b1111111111 %
b1111111111 )
#123
1$
#124
0$
#132
b100000000 "
b100000000 +
b100000000 !
b100000000 ,
