alu.v
/*
* ALU con operandi a N bit. Implementa le operazioni di somma, sottrazione, incremento, decremento e divisione.
* Fornisce in output, oltre al risultato, anche un bit di segno.
*/
module ALU(output reg [N-1:0]z, output reg segno, input [N-1:0]x, input [N-1:0]y, input [2:0]alpha);
  parameter N = 32;
  parameter RITARDO = 10;

  always @(alpha or x or y)
  begin
    #RITARDO;
    case(alpha)
      0: z = x + y;
      1: z = x - y;
      2: z = x + 1;
      3: z = x - 1;
      4: z = y + 1;
      5: z = y - 1;
      6: z = x / y;
    endcase
    segno = z[N-1]; // bit di segno
  end
endmodule

test_alu.v
module test_alu();
  reg [2:0]alpha = 0;
  reg [31:0]x = 0;
  reg [31:0]y = 0;
  wire signed [31:0]z;
  wire segno;

  ALU#(32, 10) alu(z, segno, x, y, alpha);

  initial
  begin
    $dumpfile("test_alu.vcd");
    $dumpvars;

    #11 $display("%t alpha:%d x:%d y:%d x+y: %d", $time, alpha, x, y, z);

    x = 10;
    y = 5;
    #11 $display("%t alpha:%d x:%d y:%d x+y: %d", $time, alpha, x, y, z);

    x = 20;
    y = 4;
    alpha = 3'b001; // uso della base binaria
    #11 $display("%t alpha:%d x:%d y:%d x-y: %d", $time, alpha, x, y, z);

    x = 1;
    y = 10;
    #11 $display("%t alpha:%d x:%d y:%d x-y: %d", $time, alpha, x, y, z);

    alpha = 3'd3; // uso della base decimale
    #11 $display("%t alpha:%d x:%d y:%d x-1: %d", $time, alpha, x, y, z);

    alpha = 6; // uso della costante decimale 6 invece di 3'd6
    #11 $display("%t alpha:%d x:%d y:%d x/y: %d", $time, alpha, x, y, z);

    #11 $finish;
  end

endmodule

test_alu.vcd
$date
	Mon Aug 26 23:40:14 2019
$end
$version
	Icarus Verilog
$end
$timescale
	1s
$end
$scope module test_alu $end
$var wire 32 ! z [31:0] $end
$var wire 1 " segno $end
$var reg 3 # alpha [2:0] $end
$var reg 32 $ x [31:0] $end
$var reg 32 % y [31:0] $end
$scope module alu $end
$var wire 3 & alpha [2:0] $end
$var wire 32 ' x [31:0] $end
$var wire 32 ( y [31:0] $end
$var reg 1 " segno $end
$var reg 32 ) z [31:0] $end
$upscope $end
$upscope $end
$enddefinitions $end
#0
$dumpvars
bx )
b0 (
b0 '
b0 &
b0 %
b0 $
b0 #
x"
bx !
$end
#10
0"
b0 !
b0 )
#11
b101 %
b101 (
b1010 $
b1010 '
#21
b1111 !
b1111 )
#22
b1 #
b1 &
b100 %
b100 (
b10100 $
b10100 '
#32
b10000 !
b10000 )
#33
b1010 %
b1010 (
b1 $
b1 '
#43
1"
b11111111111111111111111111110111 !
b11111111111111111111111111110111 )
#44
b11 #
b11 &
#54
0"
b0 !
b0 )
#55
b110 #
b110 &
