confrontatore.v
/*
* Confrontatore con 2 ingressi da un bit: calcola 0 se i due bit in ingresso sono uguali, 1 altrimenti
*/

module CONFRONTATORE(output out, input x1, input x2);
  assign #2 out = x1 ^ x2; // operatore xor
endmodule

registro.v
/*
* Registro impulsato da N bit
*/
module REGISTRO(output [N-1:0]out, input [N-1:0]in, input clock, input beta);
  parameter N = 32;
  reg [N-1:0]val = 0;

  // Si scrive nel registro durante il fronte di alzata per evitare stati metastabili
  // all'avvio del programma, per esempio:
  // in un'interfaccia a transizione di livello il registro interno S ha il beta=1 costante.
  // Questo implica che all'avvio della simulazione venga scritto nel registro il valore della linea
  // di ingresso (per esempio la linea rdy). Se questa linea impiega un tempo t > 0 per stabilizzare, nel
  // registro viene scritto all'avvio della simulazione (perche` clock = 0 al tempo t=0 viene interpretato
  // come un negedge del segnale di clock) un valore instabile che dura fino al prossimo impulso del clock.
  // Utilizzando posedge ed avendo l'accortezza di inizializzare il registro a 0 (in cima, val = 0) e di
  // generare il segnale di clock partendo dal basso( ____|¯¯|____|¯¯|_) si evita questo problema, purche` al
  // prossimo impulso di clock l'ingresso del registro sia stabile.
  always @(posedge clock)
  begin
    if (beta)
      val <= in;
  end

  assign out = val;
endmodule

transizione_livello.v
module TRANSIZIONE_LIVELLO(output out, input in, input clock, input beta);

  wire s_out;
  reg contatore_mod_2 = 0; // conta mod 2 quante volte beta diventa 1

  REGISTRO#(1) s(s_out, in, clock, 1'b1);
  CONFRONTATORE c(out, s_out, contatore_mod_2);

  // 2tp di ritardo per il contatore modulo 2
  always @(beta)
  begin
    #2 contatore_mod_2 = contatore_mod_2 ^ beta;
  end

endmodule

test_transizione_livello.v
module test_transizione_livello();

  reg clock = 0;
  reg beta_rdyin = 0;
  reg beta_rdyout = 0;
  wire rdy_out;
  wire rdy_in;

  TRANSIZIONE_LIVELLO rdyout(rdy_out, 1'b0, clock, beta_rdyout);
  TRANSIZIONE_LIVELLO rdyin(rdy_in, rdy_out, clock, beta_rdyin);

  always
  begin
    if (clock == 0)
      #6 clock = 1;
    else 
      #1 clock = 0;
  end

  initial
  begin
    $dumpfile("test_transizione_livello.vcd");
    $dumpvars;
    // Notifica invio messaggio (set RDYout)
    #9 beta_rdyout = 1;
    #7 beta_rdyout = 0;

    // Ricezione messaggio (reset RDYin)
    #12 beta_rdyin = 1;
    #6 beta_rdyin = 0;

    // Notifica invio messaggio (set RDYout)
    #12 beta_rdyout = 1;
    #6 beta_rdyout = 0;

    // Ricezione messaggio (reset RDYin)
    #12 beta_rdyin = 1;
    #6 beta_rdyin = 0;

    #200;
    $finish;
  end
  
endmodule

test_transizione_livello.vcd
$date
	Sat Aug 31 12:47:19 2019
$end
$version
	Icarus Verilog
$end
$timescale
	1s
$end
$scope module test_transizione_livello $end
$var wire 1 ! rdy_out $end
$var wire 1 " rdy_in $end
$var reg 1 # beta_rdyin $end
$var reg 1 $ beta_rdyout $end
$var reg 1 % clock $end
$scope module rdyin $end
$var wire 1 # beta $end
$var wire 1 % clock $end
$var wire 1 & s_out $end
$var wire 1 " out $end
$var wire 1 ! in $end
$var reg 1 ' contatore_mod_2 $end
$scope module c $end
$var wire 1 " out $end
$var wire 1 ' x2 $end
$var wire 1 & x1 $end
$upscope $end
$scope module s $end
$var wire 1 ( beta $end
$var wire 1 % clock $end
$var wire 1 & out $end
$var wire 1 ! in $end
$var reg 1 & val $end
$upscope $end
$upscope $end
$scope module rdyout $end
$var wire 1 $ beta $end
$var wire 1 % clock $end
$var wire 1 ) in $end
$var wire 1 * s_out $end
$var wire 1 ! out $end
$var reg 1 + contatore_mod_2 $end
$scope module c $end
$var wire 1 ! out $end
$var wire 1 + x2 $end
$var wire 1 * x1 $end
$upscope $end
$scope module s $end
$var wire 1 , beta $end
$var wire 1 % clock $end
$var wire 1 ) in $end
$var wire 1 * out $end
$var reg 1 * val $end
$upscope $end
$upscope $end
$upscope $end
$enddefinitions $end
#0
$dumpvars
1,
0+
0*
0)
1(
0'
0&
0%
0$
0#
x"
x!
$end
#2
0!
0"
#6
1%
#7
0%
#9
1$
#11
1+
#13
1&
1!
1%
#14
0%
#15
1"
#16
0$
#20
1%
#21
0%
#27
1%
#28
0%
1#
#30
1'
#32
0"
#34
1%
0#
#35
0%
#41
1%
#42
0%
#46
1$
#48
0+
1%
#49
0%
#50
0!
#52
0$
#55
0&
1%
#56
0%
#57
1"
#62
1%
#63
0%
#64
1#
#66
0'
#68
0"
#69
1%
#70
0%
0#
