memoria.v
/*
* Memoria a doppia porta da N posizioni ciascuna da M bit:
* - 1 porta in lettura/scrittura
* - 1 porta in lettura;
* Il ritardo di accesso in memoria e` parametrizzabile, di default e` uguale a 8tp.
* TODO: aggiornare documento di derivazione formale: la memoria e` a doppia porta, non tripla e va aggiunto il segnale di clock, beta, il valore di ingresso e rimuovere alpha.
*/
module MEMORIA(out1, out2, in, ind1, ind2, clock, beta);

  parameter N=1024;
  parameter M=32;
  parameter RITARDO=8;
  parameter IND_SIZE=$clog2(N);

  output [M-1:0]out1, out2;
  input [M-1:0]in;
  input [IND_SIZE-1:0]ind1, ind2;
  input clock;
  input beta; // beta = 1, abilita scrittura in mem[ind1]
  integer i;

  reg [M-1:0]mem[0:N-1];

  initial
  begin
    for (i=0; i<N; i++)
      mem[i] = 0;
  end

  always @(negedge clock)
  begin
    if(beta)
      mem[ind1] = in;
  end

  assign #RITARDO out1 = mem[ind1];
  assign #RITARDO out2 = mem[ind2];

endmodule

alu.v
/*
* ALU con operandi a N bit. Implementa le operazioni di somma, sottrazione, incremento, decremento e divisione.
* Fornisce in output, oltre al risultato, anche un bit di segno.
*/
module ALU(output reg [N-1:0]z, output reg segno, input [N-1:0]x, input [N-1:0]y, input [2:0]alpha);
  parameter N = 32;
  parameter RITARDO = 10;

  always @(alpha or x or y)
  begin
    #RITARDO;
    case(alpha)
      0: z = x + y;
      1: z = x - y;
      2: z = x + 1;
      3: z = x - 1;
      4: z = y + 1;
      5: z = y - 1;
      6: z = x / y;
    endcase
    segno = ~z[N-1]; // bit di segno negato (i.e. 0 se il risultato e` negativo, 1 se e` positivo)
  end
endmodule

commutatore2.v
/*
* Commutatore da N bit a due vie con 2tp di ritardo
*/
module COMMUTATORE2 (output [N-1:0]out, input [N-1:0]x1, input [N-1:0]x2, input alpha);
  parameter N=32;
  
  assign #2 out = ((~alpha) ? x1 : x2);

endmodule

registro.v
/*
* Registro impulsato da N bit
*/
module REGISTRO(output [N-1:0]out, input [N-1:0]in, input clock, input beta);
  parameter N = 32;

  reg [N-1:0]val = 0;
  assign out = val;

  always @(negedge clock)
  begin
    if (beta)
      val = in;
  end
endmodule

po.v
module PO(output [ALU_SIZE-1:0]out,
  input clock, 
  // alpha
  input alpha_k1, 
  input alpha_k2, 
  input alpha_k3, 
  input alpha_k4, 
  input alpha_k5, 
  input alpha_k_ind,
  input alpha_k_i,
  input alpha_k_esito,
  input alpha_k_dataout,
  input alpha_k_mem1, alpha_k_mem2,
  input [2:0]alpha_alu2, 
  input [2:0]alpha_alu3, 
  input [2:0]alpha_alu4, 
  // beta
  input beta_hd,
  input beta_ind,
  input beta_i,
  input beta_esito,
  input beta_datain,
  input beta_dataout,
  input beta_mem,
  // altri input
  input [ALU_SIZE-1:0]datain_val,
  input [9:0]n_val

);

  parameter ALU_SIZE = 32;
  parameter K1_SIZE = 32;
  parameter K2_SIZE = 32;
  parameter K3_SIZE = 11;
  parameter K4_SIZE = 11;
  parameter K5_SIZE = 11;
  parameter K_IND_SIZE = 10;
  parameter K_I_SIZE = 10;
  parameter K_ESITO_SIZE = 1;

  /******* CONNESSIONI ********/
  // registri
  wire [10:0]hd_out;
  wire [K_IND_SIZE-1:0]ind_out;
  wire [K_I_SIZE-1:0]i_out;
  wire [K_ESITO_SIZE-1:0]esito_out;
  wire [ALU_SIZE-1:0]datain_out;
  wire [ALU_SIZE-1:0]dataout_out;
  wire [9:0]n_out;

  // commutatori
  wire [K1_SIZE-1:0]k1_out;
  wire [K2_SIZE-1:0]k2_out;
  wire [K3_SIZE-1:0]k3_out;
  wire [K4_SIZE-1:0]k4_out;
  wire [K5_SIZE-1:0]k5_out;
  wire [K_IND_SIZE-1:0]k_ind_out;
  wire [K_I_SIZE-1:0]k_i_out;
  wire [K_ESITO_SIZE-1:0]k_esito_out;
  wire [ALU_SIZE-1:0]k_dataout_out;
  wire [10:0]k_mem1_out, k_mem2_out;

  // alu
  wire [ALU_SIZE-1:0]alu2_out, alu3_out, alu4_out;
  wire alu2_segno, alu3_segno, alu4_segno;

  // memoria
  wire [31:0]mem_out1, mem_out2;
  /****************************/


  /******* COMPONENTI *********/
  // registri
  REGISTRO#(11) hd(hd_out, alu3_out, clock, beta_hd);
  REGISTRO#(10) ind(ind_out, k_ind_out, clock, beta_ind);
  REGISTRO#(10) i(i_out, k_i_out, clock, beta_i);
  REGISTRO#(3) esito(esito_out, k_esito_out, clock, beta_esito);
  REGISTRO#(ALU_SIZE) datain(datain_out, datain_val, clock, beta_datain); // TODO: beta sempre = 1?
  REGISTRO#(ALU_SIZE) dataout(dataout_out, k_dataout_out, clock, beta_dataout);
  REGISTRO#(10) n(n_out, n_val, clock, beta_n); //TODO: beta sempre = 1?

  // commutatori
  COMMUTATORE2#(K1_SIZE) k1(k1_out, mem_out1, dataout_out, alpha_k1);
  COMMUTATORE2#(K2_SIZE) k2(k2_out, mem_out2, n_out, alpha_k2);
  COMMUTATORE2#(K3_SIZE) k3(k3_out, hd_out, ind_out, alpha_k3);
  COMMUTATORE2#(K4_SIZE) k4(k4_out, hd_out, i_out, alpha_k4);
  COMMUTATORE2#(K5_SIZE) k5(k5_out, 1, 2, alpha_k5);
  COMMUTATORE2#(K_IND_SIZE) k_ind(k_ind_out, alu4_out, alu3_out, alpha_k_ind);
  COMMUTATORE2#(K_I_SIZE) k_i(k_i_out, 1, alu4_out, alpha_k_i);
  COMMUTATORE2#(K_ESITO_SIZE) k_esito(k_esito_out, 0, 1, alpha_k_esito);
  COMMUTATORE2#(ALU_SIZE) k_dataout(k_dataout_out, mem_out1, alu2_out, alpha_k_dataout);

  COMMUTATORE2#(11) k_mem1(k_mem1_out, hd_out, alu3_out, alpha_k_mem1);
  COMMUTATORE2#(11) k_mem2(k_mem2_out, alu4_out, ind_out, alpha_k_mem2);

  // alu
  ALU#(ALU_SIZE) alu2(alu2_out, alu2_segno, k1_out, k2_out, alpha_alu2);
  ALU#(ALU_SIZE) alu3(alu3_out, alu3_segno, k3_out, 1, alpha_alu3);
  ALU#(ALU_SIZE) alu4(alu4_out, alu4_segno, k4_out, k5_out, alpha_alu4);

  // memoria
  MEMORIA#(1024, 32) mem(mem_out1, mem_out2, datain_out, k_mem1_out, k_mem2_out, clock, beta_mem);
  /****************************/

  assign out = dataout_out;

endmodule

test_po.v
module test_po();
  reg clock = 0;
  reg alpha_k1 = 0, alpha_k2 = 0, alpha_k3 = 0, alpha_k4 = 0, alpha_k5 = 0, alpha_k_ind = 0, alpha_k_i = 0;
  reg alpha_k_esito = 0;
  reg alpha_k_dataout = 0;
  reg alpha_k_mem1 = 0, alpha_k_mem2 = 0;
  reg [2:0]alpha_alu2 = 0, alpha_alu3 = 0, alpha_alu4 = 0;
  reg beta_hd = 0, beta_ind = 0, beta_i = 0, beta_esito = 0;
  reg beta_datain = 0, beta_dataout = 0;
  reg beta_mem = 0;
  reg [31:0]datain = 0;
  reg [9:0]n = 0;

  wire signed [31:0]po_out;

  PO parte_operativa(po_out, 
    clock, 
    alpha_k1, alpha_k2, alpha_k3, alpha_k4, alpha_k5, 
    alpha_k_ind, 
    alpha_k_i,
    alpha_k_esito,
    alpha_k_dataout,
    alpha_k_mem1, alpha_k_mem2,
    alpha_alu2, alpha_alu3, alpha_alu4, 
    beta_hd, beta_ind, beta_i, beta_esito, beta_datain, beta_dataout, beta_mem,
    datain,
    n
  );

  always
  begin
    if (clock == 0)
      #40 clock = 1;
    else 
      #1 clock = 0;
  end


  initial
  begin
    $dumpfile("test_po.vcd");
    $dumpvars;
    #20;
    alpha_k_mem1 <= 0; // HD
    beta_mem <= 1;
    datain <= 10;
    beta_datain <= 1;
    #80;
    datain = 20;
    #500;
    $finish;
  end
endmodule

test_po.vcd
$date
	Thu Aug 29 22:29:24 2019
$end
$version
	Icarus Verilog
$end
$timescale
	1s
$end
$scope module test_po $end
$var wire 32 ! po_out [31:0] $end
$var reg 3 " alpha_alu2 [2:0] $end
$var reg 3 # alpha_alu3 [2:0] $end
$var reg 3 $ alpha_alu4 [2:0] $end
$var reg 1 % alpha_k1 $end
$var reg 1 & alpha_k2 $end
$var reg 1 ' alpha_k3 $end
$var reg 1 ( alpha_k4 $end
$var reg 1 ) alpha_k5 $end
$var reg 1 * alpha_k_dataout $end
$var reg 1 + alpha_k_esito $end
$var reg 1 , alpha_k_i $end
$var reg 1 - alpha_k_ind $end
$var reg 1 . alpha_k_mem1 $end
$var reg 1 / alpha_k_mem2 $end
$var reg 1 0 beta_datain $end
$var reg 1 1 beta_dataout $end
$var reg 1 2 beta_esito $end
$var reg 1 3 beta_hd $end
$var reg 1 4 beta_i $end
$var reg 1 5 beta_ind $end
$var reg 1 6 beta_mem $end
$var reg 1 7 clock $end
$var reg 32 8 datain [31:0] $end
$var reg 10 9 n [9:0] $end
$scope module parte_operativa $end
$var wire 3 : alpha_alu2 [2:0] $end
$var wire 3 ; alpha_alu3 [2:0] $end
$var wire 3 < alpha_alu4 [2:0] $end
$var wire 1 % alpha_k1 $end
$var wire 1 & alpha_k2 $end
$var wire 1 ' alpha_k3 $end
$var wire 1 ( alpha_k4 $end
$var wire 1 ) alpha_k5 $end
$var wire 1 * alpha_k_dataout $end
$var wire 1 + alpha_k_esito $end
$var wire 1 , alpha_k_i $end
$var wire 1 - alpha_k_ind $end
$var wire 1 . alpha_k_mem1 $end
$var wire 1 / alpha_k_mem2 $end
$var wire 1 0 beta_datain $end
$var wire 1 1 beta_dataout $end
$var wire 1 2 beta_esito $end
$var wire 1 3 beta_hd $end
$var wire 1 4 beta_i $end
$var wire 1 5 beta_ind $end
$var wire 1 6 beta_mem $end
$var wire 1 = beta_n $end
$var wire 1 7 clock $end
$var wire 32 > datain_val [31:0] $end
$var wire 10 ? n_val [9:0] $end
$var wire 32 @ out [31:0] $end
$var wire 10 A n_out [9:0] $end
$var wire 32 B mem_out2 [31:0] $end
$var wire 32 C mem_out1 [31:0] $end
$var wire 11 D k_mem2_out [10:0] $end
$var wire 11 E k_mem1_out [10:0] $end
$var wire 10 F k_ind_out [9:0] $end
$var wire 10 G k_i_out [9:0] $end
$var wire 1 H k_esito_out $end
$var wire 32 I k_dataout_out [31:0] $end
$var wire 11 J k5_out [10:0] $end
$var wire 11 K k4_out [10:0] $end
$var wire 11 L k3_out [10:0] $end
$var wire 32 M k2_out [31:0] $end
$var wire 32 N k1_out [31:0] $end
$var wire 10 O ind_out [9:0] $end
$var wire 10 P i_out [9:0] $end
$var wire 11 Q hd_out [10:0] $end
$var wire 1 R esito_out $end
$var wire 32 S dataout_out [31:0] $end
$var wire 32 T datain_out [31:0] $end
$var wire 1 U alu4_segno $end
$var wire 32 V alu4_out [31:0] $end
$var wire 1 W alu3_segno $end
$var wire 32 X alu3_out [31:0] $end
$var wire 1 Y alu2_segno $end
$var wire 32 Z alu2_out [31:0] $end
$scope module alu2 $end
$var wire 3 [ alpha [2:0] $end
$var wire 32 \ y [31:0] $end
$var wire 32 ] x [31:0] $end
$var reg 1 Y segno $end
$var reg 32 ^ z [31:0] $end
$upscope $end
$scope module alu3 $end
$var wire 3 _ alpha [2:0] $end
$var wire 32 ` x [31:0] $end
$var wire 32 a y [31:0] $end
$var reg 1 W segno $end
$var reg 32 b z [31:0] $end
$upscope $end
$scope module alu4 $end
$var wire 3 c alpha [2:0] $end
$var wire 32 d x [31:0] $end
$var wire 32 e y [31:0] $end
$var reg 1 U segno $end
$var reg 32 f z [31:0] $end
$upscope $end
$scope module datain $end
$var wire 1 0 beta $end
$var wire 1 7 clock $end
$var wire 32 g in [31:0] $end
$var wire 32 h out [31:0] $end
$var reg 32 i val [31:0] $end
$upscope $end
$scope module dataout $end
$var wire 1 1 beta $end
$var wire 1 7 clock $end
$var wire 32 j out [31:0] $end
$var wire 32 k in [31:0] $end
$var reg 32 l val [31:0] $end
$upscope $end
$scope module esito $end
$var wire 1 2 beta $end
$var wire 1 7 clock $end
$var wire 3 m in [2:0] $end
$var wire 3 n out [2:0] $end
$var reg 3 o val [2:0] $end
$upscope $end
$scope module hd $end
$var wire 1 3 beta $end
$var wire 1 7 clock $end
$var wire 11 p in [10:0] $end
$var wire 11 q out [10:0] $end
$var reg 11 r val [10:0] $end
$upscope $end
$scope module i $end
$var wire 1 4 beta $end
$var wire 1 7 clock $end
$var wire 10 s out [9:0] $end
$var wire 10 t in [9:0] $end
$var reg 10 u val [9:0] $end
$upscope $end
$scope module ind $end
$var wire 1 5 beta $end
$var wire 1 7 clock $end
$var wire 10 v out [9:0] $end
$var wire 10 w in [9:0] $end
$var reg 10 x val [9:0] $end
$upscope $end
$scope module k1 $end
$var wire 1 % alpha $end
$var wire 32 y x2 [31:0] $end
$var wire 32 z x1 [31:0] $end
$var wire 32 { out [31:0] $end
$upscope $end
$scope module k2 $end
$var wire 1 & alpha $end
$var wire 32 | x2 [31:0] $end
$var wire 32 } x1 [31:0] $end
$var wire 32 ~ out [31:0] $end
$upscope $end
$scope module k3 $end
$var wire 1 ' alpha $end
$var wire 11 !" x1 [10:0] $end
$var wire 11 "" x2 [10:0] $end
$var wire 11 #" out [10:0] $end
$upscope $end
$scope module k4 $end
$var wire 1 ( alpha $end
$var wire 11 $" x1 [10:0] $end
$var wire 11 %" x2 [10:0] $end
$var wire 11 &" out [10:0] $end
$upscope $end
$scope module k5 $end
$var wire 1 ) alpha $end
$var wire 11 '" x1 [10:0] $end
$var wire 11 (" x2 [10:0] $end
$var wire 11 )" out [10:0] $end
$upscope $end
$scope module k_dataout $end
$var wire 1 * alpha $end
$var wire 32 *" x2 [31:0] $end
$var wire 32 +" x1 [31:0] $end
$var wire 32 ," out [31:0] $end
$upscope $end
$scope module k_esito $end
$var wire 1 + alpha $end
$var wire 1 -" x1 $end
$var wire 1 ." x2 $end
$var wire 1 H out $end
$upscope $end
$scope module k_i $end
$var wire 1 , alpha $end
$var wire 10 /" x1 [9:0] $end
$var wire 10 0" x2 [9:0] $end
$var wire 10 1" out [9:0] $end
$upscope $end
$scope module k_ind $end
$var wire 1 - alpha $end
$var wire 10 2" x1 [9:0] $end
$var wire 10 3" x2 [9:0] $end
$var wire 10 4" out [9:0] $end
$upscope $end
$scope module k_mem1 $end
$var wire 1 . alpha $end
$var wire 11 5" x1 [10:0] $end
$var wire 11 6" x2 [10:0] $end
$var wire 11 7" out [10:0] $end
$upscope $end
$scope module k_mem2 $end
$var wire 1 / alpha $end
$var wire 11 8" x1 [10:0] $end
$var wire 11 9" x2 [10:0] $end
$var wire 11 :" out [10:0] $end
$upscope $end
$scope module mem $end
$var wire 1 6 beta $end
$var wire 1 7 clock $end
$var wire 32 ;" in [31:0] $end
$var wire 10 <" ind1 [9:0] $end
$var wire 10 =" ind2 [9:0] $end
$var wire 32 >" out1 [31:0] $end
$var wire 32 ?" out2 [31:0] $end
$var integer 32 @" i [31:0] $end
$upscope $end
$scope module n $end
$var wire 1 = beta $end
$var wire 1 7 clock $end
$var wire 10 A" in [9:0] $end
$var wire 10 B" out [9:0] $end
$var reg 10 C" val [9:0] $end
$upscope $end
$upscope $end
$upscope $end
$enddefinitions $end
#0
$dumpvars
b0 C"
b0 B"
b0 A"
b10000000000 @"
bx ?"
bx >"
bx ="
bx <"
b0 ;"
bx :"
b0 9"
bx 8"
bx 7"
bx 6"
b0 5"
bx 4"
bx 3"
bx 2"
bx 1"
bx 0"
b1 /"
1."
0-"
bx ,"
bx +"
bx *"
bx )"
b10 ("
b1 '"
bx &"
b0 %"
b0 $"
bx #"
b0 ""
b0 !"
bx ~
bx }
b0 |
bx {
bx z
b0 y
b0 x
bx w
b0 v
b0 u
bx t
b0 s
b0 r
b0 q
bx p
b0 o
b0 n
b0x m
b0 l
bx k
b0 j
b0 i
b0 h
b0 g
bx f
b0xxxxxxxxxxx e
b0xxxxxxxxxxx d
b0 c
bx b
b1 a
b0xxxxxxxxxxx `
b0 _
bx ^
bx ]
bx \
b0 [
bx Z
xY
bx X
xW
bx V
xU
b0 T
b0 S
0R
b0 Q
b0 P
b0 O
bx N
bx M
bx L
bx K
bx J
bx I
xH
bx G
bx F
bx E
bx D
bx C
bx B
b0 A
b0 @
b0 ?
b0 >
z=
b0 <
b0 ;
b0 :
b0 9
b0 8
07
06
05
04
03
02
01
00
0/
0.
0-
0,
0+
0*
0)
0(
0'
0&
0%
b0 $
b0 #
b0 "
b0 !
$end
#2
b0 <"
b0 E
b0 7"
b1 G
b1 t
b1 1"
b0 d
b0 K
b0 &"
b0 `
b0 L
b0 #"
b0 m
0H
b1 e
b1 J
b1 )"
#10
b1 8"
b1 0"
b1 2"
b1 6"
b1 3"
b1 p
b0 C
b0 z
b0 +"
b0 >"
0U
b1 V
b1 f
0W
b1 X
b1 b
#12
b1 ="
b1 D
b1 :"
b1 F
b1 w
b1 4"
b0 I
b0 k
b0 ,"
b0 N
b0 ]
b0 {
#20
10
b1010 8
b1010 >
b1010 g
16
b0 B
b0 }
b0 ?"
#22
b0 M
b0 \
b0 ~
#32
0Y
b0 Z
b0 ^
b0 *"
#40
17
#41
b1010 T
b1010 h
b1010 ;"
b1010 i
07
#49
b1010 C
b1010 z
b1010 +"
b1010 >"
#51
b1010 I
b1010 k
b1010 ,"
b1010 N
b1010 ]
b1010 {
#61
b1010 Z
b1010 ^
b1010 *"
#81
17
#82
07
#100
b10100 8
b10100 >
b10100 g
#122
17
#123
b10100 T
b10100 h
b10100 ;"
b10100 i
07
#131
b10100 C
b10100 z
b10100 +"
b10100 >"
#133
b10100 I
b10100 k
b10100 ,"
b10100 N
b10100 ]
b10100 {
#143
b10100 Z
b10100 ^
b10100 *"
